champollion/__init__.py
champollion/_version.py
champollion/viewcode.py
champollion/directive/__init__.py
champollion/directive/base.py
champollion/directive/js_class.py
champollion/directive/js_data.py
champollion/directive/js_function.py
champollion/directive/js_module.py
champollion/directive/rst_generator.py
champollion/parser/__init__.py
champollion/parser/helper.py
champollion/parser/js_class.py
champollion/parser/js_data.py
champollion/parser/js_file.py
champollion/parser/js_function.py
champollion/parser/js_module.py
champollion-0.6.0.dist-info/DESCRIPTION.rst
champollion-0.6.0.dist-info/METADATA
champollion-0.6.0.dist-info/RECORD
champollion-0.6.0.dist-info/WHEEL
champollion-0.6.0.dist-info/metadata.json
champollion-0.6.0.dist-info/top_level.txt
