Metadata-Version: 2.0
Name: champollion
Version: 0.6.0
Summary: Sphinx extension to document javascript code.
Home-page: http://github.com/buddly27/champollion
Author: Jeremy Retailleau
Author-email: UNKNOWN
License: UNKNOWN
Keywords: sphinx,javascript,es6,restructuredtext,auto
Platform: any
Requires-Dist: sphinx (>=1.6.2,<2)
Provides-Extra: dev
Requires-Dist: lowdown (>=0.1.0,<2); extra == 'dev'
Requires-Dist: pytest (>=3.1.2,<4); extra == 'dev'
Requires-Dist: pytest-catchlog (>=1,<2); extra == 'dev'
Requires-Dist: pytest-cov (<3,>=2); extra == 'dev'
Requires-Dist: pytest-mock (>=0.6,<1); extra == 'dev'
Requires-Dist: pytest-runner (>=2.11,<3); extra == 'dev'
Requires-Dist: pytest-xdist (>=1.1,<2); extra == 'dev'
Requires-Dist: sphinx-rtd-theme (>=0.2.0,<1); extra == 'dev'
Provides-Extra: doc
Requires-Dist: lowdown (>=0.1.0,<2); extra == 'doc'
Requires-Dist: sphinx-rtd-theme (>=0.2.0,<1); extra == 'doc'
Provides-Extra: test
Requires-Dist: pytest (>=3.1.2,<4); extra == 'test'
Requires-Dist: pytest-catchlog (>=1,<2); extra == 'test'
Requires-Dist: pytest-cov (<3,>=2); extra == 'test'
Requires-Dist: pytest-mock (>=0.6,<1); extra == 'test'
Requires-Dist: pytest-runner (>=2.11,<3); extra == 'test'
Requires-Dist: pytest-xdist (>=1.1,<2); extra == 'test'
